servicemon/__init__.py
servicemon/__main__.py
servicemon/_astropy_init.py
servicemon/cone.py
servicemon/conftest.py
servicemon/pyvo_wrappers.py
servicemon/query.py
servicemon/query_runner.py
servicemon/query_stats.py
servicemon/run_utils.py
servicemon/version.py
servicemon/data/README.rst
servicemon/data/cones.py
servicemon/data/csc_cone.py
servicemon/data/csc_tap.py
servicemon/data/ps_cone.py
servicemon/data/ps_tap.py
servicemon/data/sample.py
servicemon/data/services.py
servicemon/data/vo_2mass.py
servicemon/data/vo_2mass_gavo_tap.py
servicemon/data/vo_2mass_ipac_cone.py
servicemon/data/vo_2mass_ipac_tap.py
servicemon/data/vo_services.py
servicemon/extern/__init__.py
servicemon/tests/__init__.py
servicemon/tests/coveragerc
servicemon/tests/setup_package.py
servicemon/tests/test_cone.py
servicemon/tests/test_query_stats.py
servicemon/tests/test_run_utils.py
servicemon/utils/__init__.py
servicemon/utils/tests/__init__.py
servicemon-0.0.dev75.data/scripts/servicemon
servicemon-0.0.dev75.data/scripts/servicemon_run_all
servicemon-0.0.dev75.data/scripts/servicemon_run_helper
servicemon-0.0.dev75.dist-info/METADATA
servicemon-0.0.dev75.dist-info/WHEEL
servicemon-0.0.dev75.dist-info/entry_points.txt
servicemon-0.0.dev75.dist-info/top_level.txt
servicemon-0.0.dev75.dist-info/RECORD
