Metadata-Version: 2.1
Name: servicemon
Version: 0.0.dev75
Summary: Measure/monitor VO service performance
Home-page: http://docs.astropy.org/projects/package-template/
Author: Tom Donaldson
Author-email: 
License: BSD 3-Clause
Platform: UNKNOWN
Requires-Python: >=3.7
Requires-Dist: astroquery
Requires-Dist: requests
Requires-Dist: pyvo
Requires-Dist: codetiming
